{
  "name": "Lyra",
  "race": "Elf",
  "character_class": "Wizard",
  "level": 3,
  "strength": 8,
  "dexterity": 18,
  "constitution": 12,
  "intelligence": 17,
  "wisdom": 13,
  "charisma": 10,
  "hit_points": 17,
  "armor_class": 14,
  "proficiency_bonus": 2,
  "background": "Adventurer",
  "alignment": "Chaotic Good",
  "race_traits": [],
  "class_features": [
    "Spellcasting",
    "Arcane Recovery",
    "Spell Slots: 1st: 4, 2st: 2",
    "(SRD-enhanced)"
  ],
  "proficiencies": [
    "Weapons: Daggers, darts, slings, quarterstaffs, light crossbows",
    "Saves: Intelligence, Wisdom"
  ],
  "equipment": [],
  "spells": [
    "Vicious Mockery (Enchantment 0)",
    "True Strike (Divination 0)"
  ],
  "gold": 100,
  "image_path": null
}